python_smpp-0.1.9.dist-info/DESCRIPTION.rst
python_smpp-0.1.9.dist-info/METADATA
python_smpp-0.1.9.dist-info/RECORD
python_smpp-0.1.9.dist-info/WHEEL
python_smpp-0.1.9.dist-info/metadata.json
python_smpp-0.1.9.dist-info/top_level.txt
smpp/__init__.py
smpp/clickatell.py
smpp/esme.py
smpp/pdu.py
smpp/pdu_builder.py
smpp/pdu_inspector.py
smpp/smsc.py
test/__init__.py
test/pdu.py
test/pdu_asserts.py
test/pdu_hex.py
test/pdu_hex_asserts.py
test/test_multipart.py
