Metadata-Version: 2.0
Name: python-smpp
Version: 0.1.9
Summary: Python SMPP Library
Home-page: http://github.com/praekelt/python-smpp
Author: Praekelt Foundation
Author-email: dev@praekeltfoundation.org
License: BSD
Platform: UNKNOWN
Classifier: Development Status :: 4 - Beta
Classifier: Intended Audience :: Developers
Classifier: License :: OSI Approved :: BSD License
Classifier: Operating System :: OS Independent
Classifier: Programming Language :: Python
Classifier: Topic :: Software Development :: Libraries :: Python Modules
